
{
  "Date": "2018-07-31T20:19:34.385Z",
  "Demo Created": true,
  "Login Successful": true,
  "Shell Accounts Created": true
}

{
  "Date": "2018-07-31T20:41:46.446Z",
  "Demo Created": true,
  "Login Successful": true,
  "Shell Accounts Created": true
}

{
  "Date": "2018-07-31T21:33:39.265Z",
  "Demo Created": true,
  "Login Successful": true,
  "Shell Accounts Created": true
}

{
  "Date": "2018-07-31T23:19:09.912Z",
  "Demo Created": true,
  "Login Successful": true,
  "Shell Accounts Created": true
}
